dqcsim-0.4.1.dist-info/WHEEL
dqcsim-0.4.1.dist-info/LICENSE
dqcsim-0.4.1.dist-info/RECORD
dqcsim-0.4.1.dist-info/top_level.txt
dqcsim-0.4.1.dist-info/METADATA
dqcsim.libs/libdqcsim-1d9ec6ee.so
dqcsim-0.4.1.data/data/lib/libdqcsim.so
dqcsim-0.4.1.data/data/lib/cmake/dqcsim/dqcsimConfig.cmake
dqcsim-0.4.1.data/data/lib/cmake/dqcsim/dqcsimConfigVersion.cmake
dqcsim-0.4.1.data/data/bin/dqcsfenull
dqcsim-0.4.1.data/data/bin/dqcsoppy
dqcsim-0.4.1.data/data/bin/dqcsbenull
dqcsim-0.4.1.data/data/bin/dqcsopnull
dqcsim-0.4.1.data/data/bin/dqcsfepy
dqcsim-0.4.1.data/data/bin/dqcsbepy
dqcsim-0.4.1.data/data/bin/dqcsim
dqcsim-0.4.1.data/data/include/dqcsim.h
dqcsim-0.4.1.data/data/include/cdqcsim
dqcsim-0.4.1.data/data/include/dqcsim
dqcsim-0.4.1.data/data/lib64/libdqcsim.so
dqcsim/__init__.py
dqcsim/_dqcsim.cpython-37m-x86_64-linux-gnu.so
dqcsim/plugin/__init__.py
dqcsim/host/__init__.py
dqcsim/common/qbset.py
dqcsim/common/handle.py
dqcsim/common/__init__.py
dqcsim/common/cq.py
dqcsim/common/cmd.py
dqcsim/common/mset.py
dqcsim/common/meas.py
dqcsim/common/arb.py
dqcsim/tests/null_frontend.py
dqcsim/tests/null_backend.py
dqcsim/tests/null_operator.py
dqcsim/tests/test_simulator.py
dqcsim/tests/test_allocate_free.py
dqcsim/tests/test_arb.py
dqcsim/tests/test_cmd.py
dqcsim/tests/__init__.py
dqcsim/tests/test_cq.py
dqcsim/tests/test_handle.py
dqcsim/tests/test_gatestream_misc.py
dqcsim/tests/test_qbset.py
dqcsim/tests/test_processes.py
dqcsim/tests/test_gate.py
dqcsim/tests/test_plugin.py
dqcsim/tests/test_meas.py
dqcsim/tests/test_mset.py
