Metadata-Version: 2.1
Name: dqcsim
Version: 0.4.1
Summary: Python bindings for DQCsim
Home-page: https://github.com/qe-lab/dqcsim
Author: Quantum Computer Architectures, Quantum & Computer Engineering, QuTech, Delft University of Technology
Author-email: 
License: Apache-2.0
Project-URL: Bug Tracker, https://github.com/qe-lab/dqcsim/issues
Project-URL: Documentation, https://qe-lab.github.io/dqcsim/
Project-URL: Source Code, https://github.com/qe-lab/dqcsim/
Platform: UNKNOWN
Classifier: License :: OSI Approved :: Apache Software License
Classifier: Operating System :: POSIX :: Linux
Classifier: Operating System :: MacOS
Classifier: Programming Language :: C
Classifier: Programming Language :: C++
Classifier: Programming Language :: Rust
Classifier: Programming Language :: Python :: 3 :: Only
Classifier: Programming Language :: Python :: 3.5
Classifier: Programming Language :: Python :: 3.6
Classifier: Programming Language :: Python :: 3.7
Classifier: Programming Language :: Python :: 3.8
Classifier: Topic :: Scientific/Engineering
Requires-Dist: cbor
